CMakeLists.txt
MANIFEST.in
setup.py
test.py
dist/omp_wrapper-0.1.tar.gz
dist/omp_wrapper-0.2.tar.gz
dist/omp_wrapper-0.3.tar.gz
dist/omp_wrapper-0.4.tar.gz
dist/omp_wrapper-0.5.tar.gz
dist/omp_wrapper-0.6.tar.gz
lib/pybind11/.appveyor.yml
lib/pybind11/.gitignore
lib/pybind11/.gitmodules
lib/pybind11/.readthedocs.yml
lib/pybind11/.travis.yml
lib/pybind11/CMakeLists.txt
lib/pybind11/CONTRIBUTING.md
lib/pybind11/ISSUE_TEMPLATE.md
lib/pybind11/LICENSE
lib/pybind11/MANIFEST.in
lib/pybind11/README.md
lib/pybind11/setup.cfg
lib/pybind11/setup.py
lib/pybind11/docs/Doxyfile
lib/pybind11/docs/Makefile
lib/pybind11/docs/basics.rst
lib/pybind11/docs/benchmark.py
lib/pybind11/docs/benchmark.rst
lib/pybind11/docs/changelog.rst
lib/pybind11/docs/classes.rst
lib/pybind11/docs/compiling.rst
lib/pybind11/docs/conf.py
lib/pybind11/docs/faq.rst
lib/pybind11/docs/index.rst
lib/pybind11/docs/intro.rst
lib/pybind11/docs/limitations.rst
lib/pybind11/docs/pybind11-logo.png
lib/pybind11/docs/pybind11_vs_boost_python1.png
lib/pybind11/docs/pybind11_vs_boost_python1.svg
lib/pybind11/docs/pybind11_vs_boost_python2.png
lib/pybind11/docs/pybind11_vs_boost_python2.svg
lib/pybind11/docs/reference.rst
lib/pybind11/docs/release.rst
lib/pybind11/docs/requirements.txt
lib/pybind11/docs/_static/theme_overrides.css
lib/pybind11/docs/advanced/classes.rst
lib/pybind11/docs/advanced/exceptions.rst
lib/pybind11/docs/advanced/functions.rst
lib/pybind11/docs/advanced/misc.rst
lib/pybind11/docs/advanced/smart_ptrs.rst
lib/pybind11/docs/advanced/cast/chrono.rst
lib/pybind11/docs/advanced/cast/custom.rst
lib/pybind11/docs/advanced/cast/eigen.rst
lib/pybind11/docs/advanced/cast/functional.rst
lib/pybind11/docs/advanced/cast/index.rst
lib/pybind11/docs/advanced/cast/overview.rst
lib/pybind11/docs/advanced/cast/stl.rst
lib/pybind11/docs/advanced/cast/strings.rst
lib/pybind11/docs/advanced/pycpp/index.rst
lib/pybind11/docs/advanced/pycpp/numpy.rst
lib/pybind11/docs/advanced/pycpp/object.rst
src/omp_wrapper.egg-info/PKG-INFO
src/omp_wrapper.egg-info/SOURCES.txt
src/omp_wrapper.egg-info/dependency_links.txt
src/omp_wrapper.egg-info/not-zip-safe
src/omp_wrapper.egg-info/top_level.txt
