Metadata-Version: 1.0
Name: omp-wrapper
Version: 0.7
Summary: Python wrapper for ompeval
Home-page: UNKNOWN
Author: rawk
Author-email: UNKNOWN
License: UNKNOWN
Platform: UNKNOWN
